#[non_exhaustive]
pub struct Opcodes;

pub struct Opcode {
    pub opcode: u8,
    pub opname: &'static str,
}

#[allow(unused)]
impl Opcodes {
    pub const NOP: Opcode = Opcode { opcode: 0x00, opname: "nop" };
    pub const ACONST_NULL: Opcode = Opcode { opcode: 0x01, opname: "aconst_null" };
    pub const ICONST_M1: Opcode = Opcode { opcode: 0x02, opname: "iconst_m1" };
    pub const ICONST_0: Opcode = Opcode { opcode: 0x03, opname: "iconst_0" };
    pub const ICONST_1: Opcode = Opcode { opcode: 0x04, opname: "iconst_1" };
    pub const ICONST_2: Opcode = Opcode { opcode: 0x05, opname: "iconst_2" };
    pub const ICONST_3: Opcode = Opcode { opcode: 0x06, opname: "iconst_3" };
    pub const ICONST_4: Opcode = Opcode { opcode: 0x07, opname: "iconst_4" };
    pub const ICONST_5: Opcode = Opcode { opcode: 0x08, opname: "iconst_5" };
    pub const LCONST_0: Opcode = Opcode { opcode: 0x09, opname: "lconst_0" };
    pub const LCONST_1: Opcode = Opcode { opcode: 0x0a, opname: "lconst_1" };
    pub const FCONST_0: Opcode = Opcode { opcode: 0x0b, opname: "fconst_0" };
    pub const FCONST_1: Opcode = Opcode { opcode: 0x0c, opname: "fconst_1" };
    pub const FCONST_2: Opcode = Opcode { opcode: 0x0d, opname: "fconst_2" };
    pub const DCONST_0: Opcode = Opcode { opcode: 0x0e, opname: "dconst_0" };
    pub const DCONST_1: Opcode = Opcode { opcode: 0x0f, opname: "dconst_1" };
    pub const BIPUSH: Opcode = Opcode { opcode: 0x10, opname: "bipush" };
    pub const SIPUSH: Opcode = Opcode { opcode: 0x11, opname: "sipush" };
    pub const LDC: Opcode = Opcode { opcode: 0x12, opname: "ldc" };
    pub const LDC_W: Opcode = Opcode { opcode: 0x13, opname: "ldc_w" };
    pub const LDC2_W: Opcode = Opcode { opcode: 0x14, opname: "ldc2_w" };
    pub const ILOAD: Opcode = Opcode { opcode: 0x15, opname: "iload" };
    pub const LLOAD: Opcode = Opcode { opcode: 0x16, opname: "lload" };
    pub const FLOAD: Opcode = Opcode { opcode: 0x17, opname: "fload" };
    pub const DLOAD: Opcode = Opcode { opcode: 0x18, opname: "dload" };
    pub const ALOAD: Opcode = Opcode { opcode: 0x19, opname: "aload" };
    pub const ILOAD_0: Opcode = Opcode { opcode: 0x1a, opname: "iload_0" };
    pub const ILOAD_1: Opcode = Opcode { opcode: 0x1b, opname: "iload_1" };
    pub const ILOAD_2: Opcode = Opcode { opcode: 0x1c, opname: "iload_2" };
    pub const ILOAD_3: Opcode = Opcode { opcode: 0x1d, opname: "iload_3" };
    pub const LLOAD_0: Opcode = Opcode { opcode: 0x1e, opname: "lload_0" };
    pub const LLOAD_1: Opcode = Opcode { opcode: 0x1f, opname: "lload_1" };
    pub const LLOAD_2: Opcode = Opcode { opcode: 0x20, opname: "lload_2" };
    pub const LLOAD_3: Opcode = Opcode { opcode: 0x21, opname: "lload_3" };
    pub const FLOAD_0: Opcode = Opcode { opcode: 0x22, opname: "fload_0" };
    pub const FLOAD_1: Opcode = Opcode { opcode: 0x23, opname: "fload_1" };
    pub const FLOAD_2: Opcode = Opcode { opcode: 0x24, opname: "fload_2" };
    pub const FLOAD_3: Opcode = Opcode { opcode: 0x25, opname: "fload_3" };
    pub const DLOAD_0: Opcode = Opcode { opcode: 0x26, opname: "dload_0" };
    pub const DLOAD_1: Opcode = Opcode { opcode: 0x27, opname: "dload_1" };
    pub const DLOAD_2: Opcode = Opcode { opcode: 0x28, opname: "dload_2" };
    pub const DLOAD_3: Opcode = Opcode { opcode: 0x29, opname: "dload_3" };
    pub const ALOAD_0: Opcode = Opcode { opcode: 0x2a, opname: "aload_0" };
    pub const ALOAD_1: Opcode = Opcode { opcode: 0x2b, opname: "aload_1" };
    pub const ALOAD_2: Opcode = Opcode { opcode: 0x2c, opname: "aload_2" };
    pub const ALOAD_3: Opcode = Opcode { opcode: 0x2d, opname: "aload_3" };
    pub const IALOAD: Opcode = Opcode { opcode: 0x2e, opname: "iaload" };
    pub const LALOAD: Opcode = Opcode { opcode: 0x2f, opname: "laload" };
    pub const FALOAD: Opcode = Opcode { opcode: 0x30, opname: "faload" };
    pub const DALOAD: Opcode = Opcode { opcode: 0x31, opname: "daload" };
    pub const AALOAD: Opcode = Opcode { opcode: 0x32, opname: "aaload" };
    pub const BALOAD: Opcode = Opcode { opcode: 0x33, opname: "baload" };
    pub const CALOAD: Opcode = Opcode { opcode: 0x34, opname: "caload" };
    pub const SALOAD: Opcode = Opcode { opcode: 0x35, opname: "saload" };
    pub const ISTORE: Opcode = Opcode { opcode: 0x36, opname: "istore" };
    pub const LSTORE: Opcode = Opcode { opcode: 0x37, opname: "lstore" };
    pub const FSTORE: Opcode = Opcode { opcode: 0x38, opname: "fstore" };
    pub const DSTORE: Opcode = Opcode { opcode: 0x39, opname: "dstore" };
    pub const ASTORE: Opcode = Opcode { opcode: 0x3a, opname: "astore" };
    pub const ISTORE_0: Opcode = Opcode { opcode: 0x3b, opname: "istore_0" };
    pub const ISTORE_1: Opcode = Opcode { opcode: 0x3c, opname: "istore_1" };
    pub const ISTORE_2: Opcode = Opcode { opcode: 0x3d, opname: "istore_2" };
    pub const ISTORE_3: Opcode = Opcode { opcode: 0x3e, opname: "istore_3" };
    pub const LSTORE_0: Opcode = Opcode { opcode: 0x3f, opname: "lstore_0" };
    pub const LSTORE_1: Opcode = Opcode { opcode: 0x40, opname: "lstore_1" };
    pub const LSTORE_2: Opcode = Opcode { opcode: 0x41, opname: "lstore_2" };
    pub const LSTORE_3: Opcode = Opcode { opcode: 0x42, opname: "lstore_3" };
    pub const FSTORE_0: Opcode = Opcode { opcode: 0x43, opname: "fstore_0" };
    pub const FSTORE_1: Opcode = Opcode { opcode: 0x44, opname: "fstore_1" };
    pub const FSTORE_2: Opcode = Opcode { opcode: 0x45, opname: "fstore_2" };
    pub const FSTORE_3: Opcode = Opcode { opcode: 0x46, opname: "fstore_3" };
    pub const DSTORE_0: Opcode = Opcode { opcode: 0x47, opname: "dstore_0" };
    pub const DSTORE_1: Opcode = Opcode { opcode: 0x48, opname: "dstore_1" };
    pub const DSTORE_2: Opcode = Opcode { opcode: 0x49, opname: "dstore_2" };
    pub const DSTORE_3: Opcode = Opcode { opcode: 0x4a, opname: "dstore_3" };
    pub const ASTORE_0: Opcode = Opcode { opcode: 0x4b, opname: "astore_0" };
    pub const ASTORE_1: Opcode = Opcode { opcode: 0x4c, opname: "astore_1" };
    pub const ASTORE_2: Opcode = Opcode { opcode: 0x4d, opname: "astore_2" };
    pub const ASTORE_3: Opcode = Opcode { opcode: 0x4e, opname: "astore_3" };
    pub const IASTORE: Opcode = Opcode { opcode: 0x4f, opname: "iastore" };
    pub const LASTORE: Opcode = Opcode { opcode: 0x50, opname: "lastore" };
    pub const FASTORE: Opcode = Opcode { opcode: 0x51, opname: "fastore" };
    pub const DASTORE: Opcode = Opcode { opcode: 0x52, opname: "dastore" };
    pub const AASTORE: Opcode = Opcode { opcode: 0x53, opname: "aastore" };
    pub const BASTORE: Opcode = Opcode { opcode: 0x54, opname: "bastore" };
    pub const CASTORE: Opcode = Opcode { opcode: 0x55, opname: "castore" };
    pub const SASTORE: Opcode = Opcode { opcode: 0x56, opname: "sastore" };
    pub const POP: Opcode = Opcode { opcode: 0x57, opname: "pop" };
    pub const POP2: Opcode = Opcode { opcode: 0x58, opname: "pop2" };
    pub const DUP: Opcode = Opcode { opcode: 0x59, opname: "dup" };
    pub const DUP_X1: Opcode = Opcode { opcode: 0x5a, opname: "dup_x1" };
    pub const DUP_X2: Opcode = Opcode { opcode: 0x5b, opname: "dup_x2" };
    pub const DUP2: Opcode = Opcode { opcode: 0x5c, opname: "dup2" };
    pub const DUP2_X1: Opcode = Opcode { opcode: 0x5d, opname: "dup2_x1" };
    pub const DUP2_X2: Opcode = Opcode { opcode: 0x5e, opname: "dup2_x2" };
    pub const SWAP: Opcode = Opcode { opcode: 0x5f, opname: "swap" };
    pub const IADD: Opcode = Opcode { opcode: 0x60, opname: "iadd" };
    pub const LADD: Opcode = Opcode { opcode: 0x61, opname: "ladd" };
    pub const FADD: Opcode = Opcode { opcode: 0x62, opname: "fadd" };
    pub const DADD: Opcode = Opcode { opcode: 0x63, opname: "dadd" };
    pub const ISUB: Opcode = Opcode { opcode: 0x64, opname: "isub" };
    pub const LSUB: Opcode = Opcode { opcode: 0x65, opname: "lsub" };
    pub const FSUB: Opcode = Opcode { opcode: 0x66, opname: "fsub" };
    pub const DSUB: Opcode = Opcode { opcode: 0x67, opname: "dsub" };
    pub const IMUL: Opcode = Opcode { opcode: 0x68, opname: "imul" };
    pub const LMUL: Opcode = Opcode { opcode: 0x69, opname: "lmul" };
    pub const FMUL: Opcode = Opcode { opcode: 0x6a, opname: "fmul" };
    pub const DMUL: Opcode = Opcode { opcode: 0x6b, opname: "dmul" };
    pub const IDIV: Opcode = Opcode { opcode: 0x6c, opname: "idiv" };
    pub const LDIV: Opcode = Opcode { opcode: 0x6d, opname: "ldiv" };
    pub const FDIV: Opcode = Opcode { opcode: 0x6e, opname: "fdiv" };
    pub const DDIV: Opcode = Opcode { opcode: 0x6f, opname: "ddiv" };
    pub const IREM: Opcode = Opcode { opcode: 0x70, opname: "irem" };
    pub const LREM: Opcode = Opcode { opcode: 0x71, opname: "lrem" };
    pub const FREM: Opcode = Opcode { opcode: 0x72, opname: "frem" };
    pub const DREM: Opcode = Opcode { opcode: 0x73, opname: "drem" };
    pub const INEG: Opcode = Opcode { opcode: 0x74, opname: "ineg" };
    pub const LNEG: Opcode = Opcode { opcode: 0x75, opname: "lneg" };
    pub const FNEG: Opcode = Opcode { opcode: 0x76, opname: "fneg" };
    pub const DNEG: Opcode = Opcode { opcode: 0x77, opname: "dneg" };
    pub const ISHL: Opcode = Opcode { opcode: 0x78, opname: "ishl" };
    pub const LSHL: Opcode = Opcode { opcode: 0x79, opname: "lshl" };
    pub const ISHR: Opcode = Opcode { opcode: 0x7a, opname: "ishr" };
    pub const LSHR: Opcode = Opcode { opcode: 0x7b, opname: "lshr" };
    pub const IUSHR: Opcode = Opcode { opcode: 0x7c, opname: "iushr" };
    pub const LUSHR: Opcode = Opcode { opcode: 0x7d, opname: "lushr" };
    pub const IAND: Opcode = Opcode { opcode: 0x7e, opname: "iand" };
    pub const LAND: Opcode = Opcode { opcode: 0x7f, opname: "land" };
    pub const IOR: Opcode = Opcode { opcode: 0x80, opname: "ior" };
    pub const LOR: Opcode = Opcode { opcode: 0x81, opname: "lor" };
    pub const IXOR: Opcode = Opcode { opcode: 0x82, opname: "ixor" };
    pub const LXOR: Opcode = Opcode { opcode: 0x83, opname: "lxor" };
    pub const IINC: Opcode = Opcode { opcode: 0x84, opname: "iinc" };
    pub const I2L: Opcode = Opcode { opcode: 0x85, opname: "i2l" };
    pub const I2F: Opcode = Opcode { opcode: 0x86, opname: "i2f" };
    pub const I2D: Opcode = Opcode { opcode: 0x87, opname: "i2d" };
    pub const L2I: Opcode = Opcode { opcode: 0x88, opname: "l2i" };
    pub const L2F: Opcode = Opcode { opcode: 0x89, opname: "l2f" };
    pub const L2D: Opcode = Opcode { opcode: 0x8a, opname: "l2d" };
    pub const F2I: Opcode = Opcode { opcode: 0x8b, opname: "f2i" };
    pub const F2L: Opcode = Opcode { opcode: 0x8c, opname: "f2l" };
    pub const F2D: Opcode = Opcode { opcode: 0x8d, opname: "f2d" };
    pub const D2I: Opcode = Opcode { opcode: 0x8e, opname: "d2i" };
    pub const D2L: Opcode = Opcode { opcode: 0x8f, opname: "d2l" };
    pub const D2F: Opcode = Opcode { opcode: 0x90, opname: "d2f" };
    pub const I2B: Opcode = Opcode { opcode: 0x91, opname: "i2b" };
    pub const I2C: Opcode = Opcode { opcode: 0x92, opname: "i2c" };
    pub const I2S: Opcode = Opcode { opcode: 0x93, opname: "i2s" };
    pub const LCMP: Opcode = Opcode { opcode: 0x94, opname: "lcmp" };
    pub const FCMPL: Opcode = Opcode { opcode: 0x95, opname: "fcmpl" };
    pub const FCMPG: Opcode = Opcode { opcode: 0x96, opname: "fcmpg" };
    pub const DCMPL: Opcode = Opcode { opcode: 0x97, opname: "dcmpl" };
    pub const DCMPG: Opcode = Opcode { opcode: 0x98, opname: "dcmpg" };
    pub const IFEQ: Opcode = Opcode { opcode: 0x99, opname: "ifeq" };
    pub const IFNE: Opcode = Opcode { opcode: 0x9a, opname: "ifne" };
    pub const IFLT: Opcode = Opcode { opcode: 0x9b, opname: "iflt" };
    pub const IFGE: Opcode = Opcode { opcode: 0x9c, opname: "ifge" };
    pub const IFGT: Opcode = Opcode { opcode: 0x9d, opname: "ifgt" };
    pub const IFLE: Opcode = Opcode { opcode: 0x9e, opname: "ifle" };
    pub const IF_ICMPEQ: Opcode = Opcode { opcode: 0x9f, opname: "if_icmpeq" };
    pub const IF_ICMPNE: Opcode = Opcode { opcode: 0xa0, opname: "if_icmpne" };
    pub const IF_ICMPLT: Opcode = Opcode { opcode: 0xa1, opname: "if_icmplt" };
    pub const IF_ICMPGE: Opcode = Opcode { opcode: 0xa2, opname: "if_icmpge" };
    pub const IF_ICMPGT: Opcode = Opcode { opcode: 0xa3, opname: "if_icmpgt" };
    pub const IF_ICMPLE: Opcode = Opcode { opcode: 0xa4, opname: "if_icmple" };
    pub const IF_ACMPEQ: Opcode = Opcode { opcode: 0xa5, opname: "if_acmpeq" };
    pub const IF_ACMPNE: Opcode = Opcode { opcode: 0xa6, opname: "if_acmpne" };
    pub const GOTO: Opcode = Opcode { opcode: 0xa7, opname: "goto" };
    pub const JSR: Opcode = Opcode { opcode: 0xa8, opname: "jsr" };
    pub const RET: Opcode = Opcode { opcode: 0xa9, opname: "ret" };
    pub const TABLESWITCH: Opcode = Opcode { opcode: 0xaa, opname: "tableswitch" };
    pub const LOOKUPSWITCH: Opcode = Opcode { opcode: 0xab, opname: "lookupswitch" };
    pub const IRETURN: Opcode = Opcode { opcode: 0xac, opname: "ireturn" };
    pub const LRETURN: Opcode = Opcode { opcode: 0xad, opname: "lreturn" };
    pub const FRETURN: Opcode = Opcode { opcode: 0xae, opname: "freturn" };
    pub const DRETURN: Opcode = Opcode { opcode: 0xaf, opname: "dreturn" };
    pub const ARETURN: Opcode = Opcode { opcode: 0xb0, opname: "areturn" };
    pub const RETURN: Opcode = Opcode { opcode: 0xb1, opname: "return" };
    pub const GETSTATIC: Opcode = Opcode { opcode: 0xb2, opname: "getstatic" };
    pub const PUTSTATIC: Opcode = Opcode { opcode: 0xb3, opname: "putstatic" };
    pub const GETFIELD: Opcode = Opcode { opcode: 0xb4, opname: "getfield" };
    pub const PUTFIELD: Opcode = Opcode { opcode: 0xb5, opname: "putfield" };
    pub const INVOKEVIRTUAL: Opcode = Opcode { opcode: 0xb6, opname: "invokevirtual" };
    pub const INVOKESPECIAL: Opcode = Opcode { opcode: 0xb7, opname: "invokespecial" };
    pub const INVOKESTATIC: Opcode = Opcode { opcode: 0xb8, opname: "invokestatic" };
    pub const INVOKEINTERFACE: Opcode = Opcode { opcode: 0xb9, opname: "invokeinterface" };
    pub const INVOKEDYNAMIC: Opcode = Opcode { opcode: 0xba, opname: "invokedynamic" };
    pub const NEW: Opcode = Opcode { opcode: 0xbb, opname: "new" };
    pub const NEWARRAY: Opcode = Opcode { opcode: 0xbc, opname: "newarray" };
    pub const ANEWARRAY: Opcode = Opcode { opcode: 0xbd, opname: "anewarray" };
    pub const ARRAYLENGTH: Opcode = Opcode { opcode: 0xbe, opname: "arraylength" };
    pub const ATHROW: Opcode = Opcode { opcode: 0xbf, opname: "athrow" };
    pub const CHECKCAST: Opcode = Opcode { opcode: 0xc0, opname: "checkcast" };
    pub const INSTANCEOF: Opcode = Opcode { opcode: 0xc1, opname: "instanceof" };
    pub const MONITORENTER: Opcode = Opcode { opcode: 0xc2, opname: "monitorenter" };
    pub const MONITOREXIT: Opcode = Opcode { opcode: 0xc3, opname: "monitorexit" };
    pub const WIDE: Opcode = Opcode { opcode: 0xc4, opname: "wide" };
    pub const MULTIANEWARRAY: Opcode = Opcode { opcode: 0xc5, opname: "multianewarray" };
    pub const IFNULL: Opcode = Opcode { opcode: 0xc6, opname: "ifnull" };
    pub const IFNONNULL: Opcode = Opcode { opcode: 0xc7, opname: "ifnonnull" };
    pub const GOTO_W: Opcode = Opcode { opcode: 0xc8, opname: "goto_w" };
    pub const JSR_W: Opcode = Opcode { opcode: 0xc9, opname: "jsr_w" };
}